alluxiocommon-1.0.4.dist-info/METADATA
alluxiocommon-1.0.4.dist-info/WHEEL
alluxiocommon/__init__.py
alluxiocommon/alluxiocommon.cpython-38-x86_64-linux-gnu.so
alluxiocommon-1.0.4.dist-info/RECORD
