Metadata-Version: 2.3
Name: alluxiocommon
Version: 1.0.4
Summary: Alluxio Fsspec native enhancement module with PyO3 in rust
Author: Shufan Ge <lucy.ge@alluxio.com>
Author-email: Shufan Ge <lucy.ge@alluxio.com>
